{"version": "1", "message": "ERROR: Hidden Testcases server unreachable.", "problem_id": "ads1_m12_a1", "user_id": "Abijithhebbar", "score": {"sample": {"0": {"execution_time": 0.16443967819213867, "passed": false}, "1": {"execution_time": 0.16180109977722168, "passed": false}, "2": {"execution_time": 0.15703678131103516, "passed": false}, "3": {"execution_time": 0.15979671478271484, "passed": false}, "4": {"execution_time": 0.15862226486206055, "passed": false}, "5": {"execution_time": 0.15732693672180176, "passed": false}}}, "check_style_score": "0/1"}